sentry_dtt/__init__.py
sentry_dtt/plugin.py
sentry_dtt-1.0.4.dist-info/METADATA
sentry_dtt-1.0.4.dist-info/WHEEL
sentry_dtt-1.0.4.dist-info/entry_points.txt
sentry_dtt-1.0.4.dist-info/top_level.txt
sentry_dtt-1.0.4.dist-info/RECORD
