Metadata-Version: 2.1
Name: sentry-dtt
Version: 1.0.4
Summary: A sentry extension integrates DingTalk robot webhook
Home-page: https://github.com/lanxuexing/sentry-dingtalk-notify
Author: lanxuexing
Author-email: lanxuexing313wsr@163.com
License: MIT
Keywords: sentry dingtalk
Classifier: License :: OSI Approved :: MIT License
Classifier: Programming Language :: Python
Classifier: Programming Language :: Python :: 3
Classifier: Programming Language :: Python :: 3.6
Classifier: Programming Language :: Python :: 3.7
Classifier: Programming Language :: Python :: Implementation :: CPython
Requires-Python: >=3.6.13
Requires-Dist: sentry (>=21.5.1)
